README
setup.py
bin/theshowfinder
bin/theshowrater
theshowutil/__init__.py
theshowutil/driver.py
theshowutil/lahmandb.py
theshowutil/playerdata.py
theshowutil/ratinggenerator.py
theshowutil/view.py
theshowutil.egg-info/PKG-INFO
theshowutil.egg-info/SOURCES.txt
theshowutil.egg-info/dependency_links.txt
theshowutil.egg-info/top_level.txt