Metadata-Version: 1.1
Name: theshowutil
Version: 0.1.1
Summary: MLB the Show player rating utility
Home-page: https://github.com/nomo17k/theshowutil
Author: Taro Sato
Author-email: okomestudio@gmail.com
License: BSD
Platform: UNKNOWN
Classifier: Development Status :: 3 - Alpha
